common/__init__.py
common/error.py
common/error_handling.py
common/exceptions.py
common/version.py
common/serializers/__init__.py
common/serializers/base58_serializer.py
common/serializers/base64_serializer.py
common/serializers/compact_serializer.py
common/serializers/field.py
common/serializers/json_serializer.py
common/serializers/mapping_serializer.py
common/serializers/msgpack_serializer.py
common/serializers/serialization.py
common/serializers/signing_serializer.py
common/serializers/stream_serializer.py
common/test/__init__.py
common/test/test_compact_serializer.py
common/test/test_exceptions.py
common/test/test_fields.py
common/test/test_json_serializer.py
common/test/test_msgpack_serializer.py
common/test/test_signing_serializer.py
common/test/version/__init__.py
common/test/version/test_version.py
crypto/__init__.py
crypto/bls/__init__.py
crypto/bls/bls_bft.py
crypto/bls/bls_bft_replica.py
crypto/bls/bls_crypto.py
crypto/bls/bls_factory.py
crypto/bls/bls_key_manager.py
crypto/bls/bls_key_register.py
crypto/bls/bls_multi_signature.py
crypto/bls/indy_crypto/__init__.py
crypto/bls/indy_crypto/bls_crypto_indy_crypto.py
crypto/test/__init__.py
crypto/test/test_multi_signature.py
crypto/test/bls/__init__.py
crypto/test/bls/indy_crypto/__init__.py
crypto/test/bls/indy_crypto/test_bls_crypto_indy_crypto.py
data/__init__.py
data/domain_transactions_local_genesis
data/domain_transactions_sandbox_genesis
data/pool_transactions_local_genesis
data/pool_transactions_sandbox_genesis
indy_plenum-1.13.1.data/scripts/export-gen-txns
indy_plenum-1.13.1.data/scripts/filter_log
indy_plenum-1.13.1.data/scripts/gen_node
indy_plenum-1.13.1.data/scripts/gen_steward_key
indy_plenum-1.13.1.data/scripts/generate_plenum_pool_transactions
indy_plenum-1.13.1.data/scripts/get_keys
indy_plenum-1.13.1.data/scripts/init_bls_keys
indy_plenum-1.13.1.data/scripts/init_plenum_keys
indy_plenum-1.13.1.data/scripts/log_stats
indy_plenum-1.13.1.data/scripts/process_logs
indy_plenum-1.13.1.dist-info/LICENSE
indy_plenum-1.13.1.dist-info/METADATA
indy_plenum-1.13.1.dist-info/WHEEL
indy_plenum-1.13.1.dist-info/top_level.txt
indy_plenum-1.13.1.dist-info/RECORD
